MANIFEST.in
README.md
setup.py
missing/missing.py
python_missing.egg-info/PKG-INFO
python_missing.egg-info/SOURCES.txt
python_missing.egg-info/dependency_links.txt
python_missing.egg-info/entry_points.txt
python_missing.egg-info/requires.txt
python_missing.egg-info/top_level.txt